zalfmas_fbp/__init__.py
zalfmas_fbp/components/__init__.py
zalfmas_fbp/components/climate/__init__.py
zalfmas_fbp/components/climate/climate_service_to_datasets.py
zalfmas_fbp/components/climate/datasets_to_timeseries.py
zalfmas_fbp/components/climate/timeseries_cap_to_data.py
zalfmas_fbp/components/climate/timeseries_data_to_csv.py
zalfmas_fbp/components/climate/timeseries_data_to_monthly_aggregate.py
zalfmas_fbp/components/console/__init__.py
zalfmas_fbp/components/console/console_output.py
zalfmas_fbp/components/consumers/__init__.py
zalfmas_fbp/components/consumers/africa_calibration_consumer.py
zalfmas_fbp/components/data/__init__.py
zalfmas_fbp/components/data/transform/__init__.py
zalfmas_fbp/components/data/transform/ordered_flatten_nested_dicts.py
zalfmas_fbp/components/file/__init__.py
zalfmas_fbp/components/file/read_csv.py
zalfmas_fbp/components/file/read_file.py
zalfmas_fbp/components/file/write_file.py
zalfmas_fbp/components/geo/__init__.py
zalfmas_fbp/components/geo/create_lat_lon_coords.py
zalfmas_fbp/components/geo/get_lat_lon_grid_value.py
zalfmas_fbp/components/geo/proj_transform_coordinates.py
zalfmas_fbp/components/geo/to_geo_coord.py
zalfmas_fbp/components/grid/__init__.py
zalfmas_fbp/components/grid/use_grid_service.py
zalfmas_fbp/components/ip/__init__.py
zalfmas_fbp/components/ip/add_attribute.py
zalfmas_fbp/components/ip/copy.py
zalfmas_fbp/components/ip/lift_attributes.py
zalfmas_fbp/components/json/update_json.py
zalfmas_fbp/components/management/ilr_sowing_harvest_dates.py
zalfmas_fbp/components/models/__init__.py
zalfmas_fbp/components/models/monica/__init__.py
zalfmas_fbp/components/models/monica/create_monica_capnp_env.py
zalfmas_fbp/components/models/monica/create_monica_env.py
zalfmas_fbp/components/models/monica/create_monica_json_env.py
zalfmas_fbp/components/models/monica/write_monica_csv.py
zalfmas_fbp/components/producers/__init__.py
zalfmas_fbp/components/producers/africa_calibration_producer.py
zalfmas_fbp-0.2.28.dist-info/METADATA
zalfmas_fbp-0.2.28.dist-info/WHEEL
zalfmas_fbp-0.2.28.dist-info/licenses/LICENSE
zalfmas_fbp-0.2.28.dist-info/RECORD
