Metadata-Version: 2.4
Name: zalfmas-fbp
Version: 0.2.28
Summary: lib and tooling for Cap'n Proto-based FBP flows
License-File: LICENSE
Author: Michael Berg-Mohnicke
Author-email: michael.berg@zalf.de
Requires-Python: >=3.10,<3.14
Classifier: Programming Language :: Python :: 3
Classifier: Programming Language :: Python :: 3.10
Classifier: Programming Language :: Python :: 3.11
Classifier: Programming Language :: Python :: 3.12
Classifier: Programming Language :: Python :: 3.13
Requires-Dist: matplotlib (>=3.10.5,<4.0.0)
Requires-Dist: netcdf4 (>=1.7.2,<2.0.0)
Requires-Dist: pycapnp (>=2.1.0,<3.0.0)
Requires-Dist: pymep (>=1.0.7)
Requires-Dist: spotpy (>=1.6.6,<2.0.0)
Requires-Dist: tomli (>=2.2.1,<3)
Requires-Dist: tomli-w (>=1.2.0,<2)
Requires-Dist: zalfmas-capnp-schemas (>=0.1.41,<0.2.0)
Requires-Dist: zalfmas-common (>=0.1.35,<0.2.0)
Requires-Dist: zalfmas-services (>=0.1.16,<0.2.0)
